trakt/__init__.py
trakt/calendar.py
trakt/core.py
trakt/errors.py
trakt/movies.py
trakt/people.py
trakt/sync.py
trakt/tv.py
trakt/users.py
trakt/utils.py
trakt-3.4.0.dist-info/LICENSE
trakt-3.4.0.dist-info/METADATA
trakt-3.4.0.dist-info/WHEEL
trakt-3.4.0.dist-info/top_level.txt
trakt-3.4.0.dist-info/RECORD
