Metadata-Version: 2.1
Name: trakt
Version: 3.4.0
Summary: Pythonic abstraction layer for easier scripting of the Trakt.tv REST API.
Home-page: https://github.com/moogar0880/PyTrakt
Author: Jonathan Nappi
Author-email: moogar0880@gmail.com
License: Apache 2.0
Platform: UNKNOWN
Classifier: Development Status :: 5 - Production/Stable
Classifier: Intended Audience :: Developers
Classifier: Natural Language :: English
Classifier: License :: Freely Distributable
Classifier: Programming Language :: Python
Classifier: Programming Language :: Python :: 3
Classifier: Programming Language :: Python :: 3.6
Classifier: Programming Language :: Python :: 3.7
Classifier: Programming Language :: Python :: 3.8
Classifier: Programming Language :: Python :: 3.9
License-File: LICENSE
